{"chunk_definitions":[{"row":42,"row_count":1,"visible":true,"expansion_state":0,"options":{"engine":"r","warning":false,"message":false,"label":"unnamed-chunk-4"},"document_id":"975B5147","chunk_id":"cquebgco6r76g","chunk_label":"unnamed-chunk-2"},{"row":68,"row_count":1,"visible":true,"expansion_state":0,"options":{"engine":"r","warning":false,"message":false,"label":"unnamed-chunk-48"},"document_id":"5F5DD262","chunk_id":"ctgo399prckzn","chunk_label":"unnamed-chunk-3"},{"row":97,"row_count":1,"visible":true,"expansion_state":0,"options":{"engine":"r","warning":false,"message":false,"label":"unnamed-chunk-142"},"document_id":"5060A99F","chunk_id":"cbivfo3pcuilq","chunk_label":"unnamed-chunk-5"},{"row":124,"row_count":1,"visible":true,"expansion_state":0,"options":{"engine":"r","warning":false,"message":false,"label":"unnamed-chunk-9"},"document_id":"975B5147","chunk_id":"cnbgto5q8soit","chunk_label":"unnamed-chunk-6"},{"row":145,"row_count":1,"visible":true,"expansion_state":0,"options":{"engine":"r","warning":false,"message":false,"label":"unnamed-chunk-20"},"document_id":"975B5147","chunk_id":"cgw78xk7ci38n","chunk_label":"unnamed-chunk-7"},{"row":161,"row_count":1,"visible":true,"expansion_state":0,"options":{"engine":"r","warning":false,"message":false,"label":"unnamed-chunk-26"},"document_id":"975B5147","chunk_id":"cwndypd4p9r72","chunk_label":"unnamed-chunk-7"},{"row":185,"row_count":1,"visible":true,"expansion_state":0,"options":{"engine":"r","warning":false,"message":false,"label":"unnamed-chunk-25"},"document_id":"5F5DD262","chunk_id":"c1qn3tbjbqzni","chunk_label":""},{"row":207,"row_count":1,"visible":true,"expansion_state":0,"options":{"engine":"r","warning":false,"message":false,"label":"unnamed-chunk-147"},"document_id":"5F5DD262","chunk_id":"clzxvxls63cus","chunk_label":""},{"row":228,"row_count":1,"visible":true,"expansion_state":0,"options":{"engine":"r","warning":false,"message":false,"label":"unnamed-chunk-56"},"document_id":"5F5DD262","chunk_id":"cyc0o7h3j1cwb","chunk_label":""},{"row":269,"row_count":1,"visible":true,"expansion_state":0,"options":{"engine":"r","warning":false,"message":false,"label":"unnamed-chunk-100"},"document_id":"5060A99F","chunk_id":"crckaepotyo09","chunk_label":""}],"doc_write_time":1624527525}